{
    "cy": "{\"elements\":{\"nodes\":[{\"data\":{\"label\":\"Shackles of the Invoker\",\"id\":\"Node2\"},\"position\":{\"x\":-760,\"y\":40},\"group\":\"nodes\",\"removed\":false,\"selected\":false,\"selectable\":true,\"locked\":false,\"grabbable\":true,\"classes\":\"\"},{\"data\":{\"label\":\"Pride of the Invoker\",\"id\":\"Node3\"},\"position\":{\"x\":-760,\"y\":120},\"group\":\"nodes\",\"removed\":false,\"selected\":false,\"selectable\":true,\"locked\":false,\"grabbable\":true,\"classes\":\"\"},{\"data\":{\"label\":\"Renewal of the Invoker\",\"id\":\"Node4\"},\"position\":{\"x\":-760,\"y\":200},\"group\":\"nodes\",\"removed\":false,\"selected\":false,\"selectable\":true,\"locked\":false,\"grabbable\":true,\"classes\":\"\"},{\"data\":{\"label\":\"Crown of the Invoker\",\"id\":\"Node5\"},\"position\":{\"x\":-760,\"y\":280},\"group\":\"nodes\",\"removed\":false,\"selected\":false,\"selectable\":true,\"locked\":false,\"grabbable\":true,\"classes\":\"\"},{\"data\":{\"label\":\"Burden of the Invoker\",\"id\":\"Node6\"},\"position\":{\"x\":-760,\"y\":360},\"group\":\"nodes\",\"removed\":false,\"selected\":false,\"selectable\":true,\"locked\":false,\"grabbable\":true,\"classes\":\"\"},{\"data\":{\"label\":\"Zeal of the Invoker\",\"id\":\"Node7\"},\"position\":{\"x\":-760,\"y\":440},\"group\":\"nodes\",\"removed\":false,\"selected\":false,\"selectable\":true,\"locked\":false,\"grabbable\":true,\"classes\":\"\"},{\"data\":{\"label\":\"Invoker Set\",\"id\":\"Node8\"},\"position\":{\"x\":-440,\"y\":200},\"group\":\"nodes\",\"removed\":false,\"selected\":false,\"selectable\":true,\"locked\":false,\"grabbable\":true,\"classes\":\"\"},{\"data\":{\"label\":\"Equipped Gear\",\"id\":\"Node9\"},\"position\":{\"x\":-200,\"y\":200},\"group\":\"nodes\",\"removed\":false,\"selected\":false,\"selectable\":true,\"locked\":false,\"grabbable\":true,\"classes\":\"\"},{\"data\":{\"label\":\"Hack\",\"id\":\"Node10\"},\"position\":{\"x\":-440,\"y\":40},\"group\":\"nodes\",\"removed\":false,\"selected\":false,\"selectable\":true,\"locked\":false,\"grabbable\":true,\"classes\":\"\"},{\"data\":{\"label\":\"Akarat's Awakening\",\"id\":\"Node11\"},\"position\":{\"x\":-440,\"y\":-120},\"group\":\"nodes\",\"removed\":false,\"selected\":false,\"selectable\":true,\"locked\":false,\"grabbable\":true,\"classes\":\"\"},{\"data\":{\"label\":\"Belt of the Trove\",\"id\":\"Node12\"},\"position\":{\"x\":-440,\"y\":360},\"group\":\"nodes\",\"removed\":false,\"selected\":false,\"selectable\":true,\"locked\":false,\"grabbable\":true,\"classes\":\"\"},{\"data\":{\"label\":\"Traveler's Pledge\",\"id\":\"Node13\"},\"position\":{\"x\":-440,\"y\":440},\"group\":\"nodes\",\"removed\":false,\"selected\":false,\"selectable\":true,\"locked\":false,\"grabbable\":true,\"classes\":\"\"},{\"data\":{\"label\":\"Heart of Iron\",\"id\":\"Node14\"},\"position\":{\"x\":-440,\"y\":520},\"group\":\"nodes\",\"removed\":false,\"selected\":false,\"selectable\":true,\"locked\":false,\"grabbable\":true,\"classes\":\"\"},{\"data\":{\"label\":\"Boyarsky's Chip\",\"id\":\"Node15\"},\"position\":{\"x\":-760,\"y\":520},\"group\":\"nodes\",\"removed\":false,\"selected\":false,\"selectable\":true,\"locked\":false,\"grabbable\":true,\"classes\":\"\"},{\"data\":{\"label\":\"Hold Your Ground\",\"id\":\"Node16\"},\"position\":{\"x\":-200,\"y\":360},\"group\":\"nodes\",\"removed\":false,\"selected\":false,\"selectable\":true,\"locked\":false,\"grabbable\":true,\"classes\":\"\"},{\"data\":{\"label\":\"Finery\",\"id\":\"Node17\"},\"position\":{\"x\":-200,\"y\":440},\"group\":\"nodes\",\"removed\":false,\"selected\":false,\"selectable\":true,\"locked\":false,\"grabbable\":true,\"classes\":\"\"},{\"data\":{\"label\":\"Fervor\",\"id\":\"Node18\"},\"position\":{\"x\":-200,\"y\":520},\"group\":\"nodes\",\"removed\":false,\"selected\":false,\"selectable\":true,\"locked\":false,\"grabbable\":true,\"classes\":\"\"},{\"data\":{\"label\":\"Iron Maiden\",\"id\":\"Node19\"},\"position\":{\"x\":-200,\"y\":600},\"group\":\"nodes\",\"removed\":false,\"selected\":false,\"selectable\":true,\"locked\":false,\"grabbable\":true,\"classes\":\"\"},{\"data\":{\"label\":\"Passive Skills\",\"id\":\"Node20\"},\"position\":{\"x\":-40,\"y\":360},\"group\":\"nodes\",\"removed\":false,\"selected\":false,\"selectable\":true,\"locked\":false,\"grabbable\":true,\"classes\":\"\"},{\"data\":{\"label\":\"Crusader\",\"id\":\"Node21\"},\"position\":{\"x\":120,\"y\":200},\"group\":\"nodes\",\"removed\":false,\"selected\":true,\"selectable\":true,\"locked\":false,\"grabbable\":true,\"classes\":\"\"},{\"data\":{\"label\":\"Hardened Senses\",\"id\":\"Node22\"},\"position\":{\"x\":-40,\"y\":-120},\"group\":\"nodes\",\"removed\":false,\"selected\":false,\"selectable\":true,\"locked\":false,\"grabbable\":true,\"classes\":\"\"},{\"data\":{\"label\":\"Fury\",\"id\":\"Node23\"},\"position\":{\"x\":-40,\"y\":-40},\"group\":\"nodes\",\"removed\":false,\"selected\":false,\"selectable\":true,\"locked\":false,\"grabbable\":true,\"classes\":\"\"},{\"data\":{\"label\":\"Active Skills\",\"id\":\"Node24\"},\"position\":{\"x\":-40,\"y\":40},\"group\":\"nodes\",\"removed\":false,\"selected\":false,\"selectable\":true,\"locked\":false,\"grabbable\":true,\"classes\":\"\"},{\"data\":{\"label\":\"Punish\",\"id\":\"Node25\"},\"position\":{\"x\":-200,\"y\":-40},\"group\":\"nodes\",\"removed\":false,\"selected\":false,\"selectable\":true,\"locked\":false,\"grabbable\":true,\"classes\":\"\"}],\"edges\":[{\"data\":{\"source\":\"Node2\",\"target\":\"Node8\",\"id\":\"6f826e73-d86f-4754-9ddd-de3d83e96a83\"},\"position\":{\"x\":null,\"y\":null},\"group\":\"edges\",\"removed\":false,\"selected\":false,\"selectable\":true,\"locked\":false,\"grabbable\":true,\"classes\":\"\"},{\"data\":{\"source\":\"Node3\",\"target\":\"Node8\",\"id\":\"3dd98884-ae10-4480-9331-e661187f86a6\"},\"position\":{\"x\":null,\"y\":null},\"group\":\"edges\",\"removed\":false,\"selected\":false,\"selectable\":true,\"locked\":false,\"grabbable\":true,\"classes\":\"\"},{\"data\":{\"source\":\"Node4\",\"target\":\"Node8\",\"id\":\"7eea4b7f-a9b9-4f0d-aa40-f0247c88c045\"},\"position\":{\"x\":null,\"y\":null},\"group\":\"edges\",\"removed\":false,\"selected\":false,\"selectable\":true,\"locked\":false,\"grabbable\":true,\"classes\":\"\"},{\"data\":{\"source\":\"Node5\",\"target\":\"Node8\",\"id\":\"92f0f161-2fe2-4121-b669-c141dbd41c62\"},\"position\":{\"x\":null,\"y\":null},\"group\":\"edges\",\"removed\":false,\"selected\":false,\"selectable\":true,\"locked\":false,\"grabbable\":true,\"classes\":\"\"},{\"data\":{\"source\":\"Node6\",\"target\":\"Node8\",\"id\":\"6d2e8450-e2b1-4f4d-8634-9ad5922c80b0\"},\"position\":{\"x\":null,\"y\":null},\"group\":\"edges\",\"removed\":false,\"selected\":false,\"selectable\":true,\"locked\":false,\"grabbable\":true,\"classes\":\"\"},{\"data\":{\"source\":\"Node7\",\"target\":\"Node8\",\"id\":\"696f8764-658b-40b1-9f83-39cf7d414b7a\"},\"position\":{\"x\":null,\"y\":null},\"group\":\"edges\",\"removed\":false,\"selected\":false,\"selectable\":true,\"locked\":false,\"grabbable\":true,\"classes\":\"\"},{\"data\":{\"source\":\"Node8\",\"target\":\"Node9\",\"id\":\"3344ebe7-d1de-442f-8f09-b116fea3d4a0\"},\"position\":{\"x\":null,\"y\":null},\"group\":\"edges\",\"removed\":false,\"selected\":false,\"selectable\":true,\"locked\":false,\"grabbable\":true,\"classes\":\"\"},{\"data\":{\"source\":\"Node10\",\"target\":\"Node9\",\"id\":\"4f599f3f-9038-429d-908b-622977991a1d\"},\"position\":{\"x\":null,\"y\":null},\"group\":\"edges\",\"removed\":false,\"selected\":false,\"selectable\":true,\"locked\":false,\"grabbable\":true,\"classes\":\"\"},{\"data\":{\"source\":\"Node11\",\"target\":\"Node9\",\"id\":\"4241343a-d93b-4ea3-a2d8-4a25861b59b8\"},\"position\":{\"x\":null,\"y\":null},\"group\":\"edges\",\"removed\":false,\"selected\":false,\"selectable\":true,\"locked\":false,\"grabbable\":true,\"classes\":\"\"},{\"data\":{\"source\":\"Node12\",\"target\":\"Node9\",\"id\":\"9aa62f89-1375-4126-bd84-3ca5689ae210\"},\"position\":{\"x\":null,\"y\":null},\"group\":\"edges\",\"removed\":false,\"selected\":false,\"selectable\":true,\"locked\":false,\"grabbable\":true,\"classes\":\"\"},{\"data\":{\"source\":\"Node13\",\"target\":\"Node9\",\"id\":\"93cbc304-6787-4763-98fa-d1c81fda3d9d\"},\"position\":{\"x\":null,\"y\":null},\"group\":\"edges\",\"removed\":false,\"selected\":false,\"selectable\":true,\"locked\":false,\"grabbable\":true,\"classes\":\"\"},{\"data\":{\"source\":\"Node14\",\"target\":\"Node9\",\"id\":\"125f8e2f-7f81-499c-9209-e42bce3fbbc6\"},\"position\":{\"x\":null,\"y\":null},\"group\":\"edges\",\"removed\":false,\"selected\":false,\"selectable\":true,\"locked\":false,\"grabbable\":true,\"classes\":\"\"},{\"data\":{\"source\":\"Node15\",\"target\":\"Node14\",\"id\":\"248b8696-6186-4e2a-a158-b4ce43af463c\"},\"position\":{\"x\":null,\"y\":null},\"group\":\"edges\",\"removed\":false,\"selected\":false,\"selectable\":true,\"locked\":false,\"grabbable\":true,\"classes\":\"\"},{\"data\":{\"source\":\"Node16\",\"target\":\"Node20\",\"id\":\"34094f26-acd0-42f4-9a39-df4a6fcbe5c4\"},\"position\":{\"x\":null,\"y\":null},\"group\":\"edges\",\"removed\":false,\"selected\":false,\"selectable\":true,\"locked\":false,\"grabbable\":true,\"classes\":\"\"},{\"data\":{\"source\":\"Node17\",\"target\":\"Node20\",\"id\":\"9895f6cc-ab4b-4c31-b1af-ad8a75b06a0d\"},\"position\":{\"x\":null,\"y\":null},\"group\":\"edges\",\"removed\":false,\"selected\":false,\"selectable\":true,\"locked\":false,\"grabbable\":true,\"classes\":\"\"},{\"data\":{\"source\":\"Node18\",\"target\":\"Node20\",\"id\":\"81289ee5-a0c6-41c4-a672-2e8e95e7ed6c\"},\"position\":{\"x\":null,\"y\":null},\"group\":\"edges\",\"removed\":false,\"selected\":false,\"selectable\":true,\"locked\":false,\"grabbable\":true,\"classes\":\"\"},{\"data\":{\"source\":\"Node19\",\"target\":\"Node20\",\"id\":\"81566ce9-acfa-4faa-87ab-4bda6e613272\"},\"position\":{\"x\":null,\"y\":null},\"group\":\"edges\",\"removed\":false,\"selected\":false,\"selectable\":true,\"locked\":false,\"grabbable\":true,\"classes\":\"\"},{\"data\":{\"source\":\"Node25\",\"target\":\"Node23\",\"id\":\"f111cd48-ddba-4737-95cb-d58e69ee7226\"},\"position\":{\"x\":null,\"y\":null},\"group\":\"edges\",\"removed\":false,\"selected\":false,\"selectable\":true,\"locked\":false,\"grabbable\":true,\"classes\":\"\"},{\"data\":{\"source\":\"Node23\",\"target\":\"Node24\",\"id\":\"305dd962-d4af-4a28-99b0-33985c41e834\"},\"position\":{\"x\":null,\"y\":null},\"group\":\"edges\",\"removed\":false,\"selected\":false,\"selectable\":true,\"locked\":false,\"grabbable\":true,\"classes\":\"\"},{\"data\":{\"source\":\"Node25\",\"target\":\"Node22\",\"id\":\"c0a1161b-5211-4fef-bb0f-c036abfa8a5d\"},\"position\":{\"x\":null,\"y\":null},\"group\":\"edges\",\"removed\":false,\"selected\":false,\"selectable\":true,\"locked\":false,\"grabbable\":true,\"classes\":\"\"},{\"data\":{\"source\":\"Node24\",\"target\":\"Node21\",\"id\":\"8f033f82-b7d1-4e89-b564-bd86e02e8b89\"},\"position\":{\"x\":null,\"y\":null},\"group\":\"edges\",\"removed\":false,\"selected\":false,\"selectable\":true,\"locked\":false,\"grabbable\":true,\"classes\":\"\"},{\"data\":{\"source\":\"Node22\",\"target\":\"Node21\",\"id\":\"b8d76c28-f50e-412f-8718-99e78e4231c9\"},\"position\":{\"x\":null,\"y\":null},\"group\":\"edges\",\"removed\":false,\"selected\":false,\"selectable\":true,\"locked\":false,\"grabbable\":true,\"classes\":\"\"},{\"data\":{\"source\":\"Node9\",\"target\":\"Node21\",\"id\":\"8cf16c97-698f-441a-9279-9df33b7516b6\"},\"position\":{\"x\":null,\"y\":null},\"group\":\"edges\",\"removed\":false,\"selected\":false,\"selectable\":true,\"locked\":false,\"grabbable\":true,\"classes\":\"\"},{\"data\":{\"source\":\"Node20\",\"target\":\"Node21\",\"id\":\"350bca83-deb5-42b3-bfa6-71845283926d\"},\"position\":{\"x\":null,\"y\":null},\"group\":\"edges\",\"removed\":false,\"selected\":false,\"selectable\":true,\"locked\":false,\"grabbable\":true,\"classes\":\"\"}]},\"style\":[{\"selector\":\"node\",\"style\":{\"shape\":\"rectangle\",\"label\":\"data(label)\"}},{\"selector\":\"edge.highlighted\",\"style\":{\"line-color\":\"cyan\"}},{\"selector\":\"node.highlighted\",\"style\":{\"border-color\":\"cyan\",\"border-width\":\"5px\"}},{\"selector\":\"edge.highlighted\",\"style\":{\"line-color\":\"cyan\"}},{\"selector\":\"node.highlighted\",\"style\":{\"border-color\":\"cyan\",\"border-width\":\"5px\"}},{\"selector\":\"edge.highlighted\",\"style\":{\"line-color\":\"cyan\"}},{\"selector\":\"node.highlighted\",\"style\":{\"border-color\":\"cyan\",\"border-width\":\"5px\"}},{\"selector\":\"edge.highlighted\",\"style\":{\"line-color\":\"cyan\"}},{\"selector\":\"node.highlighted\",\"style\":{\"border-color\":\"cyan\",\"border-width\":\"5px\"}},{\"selector\":\"edge.highlighted\",\"style\":{\"line-color\":\"cyan\"}},{\"selector\":\"node.highlighted\",\"style\":{\"border-color\":\"cyan\",\"border-width\":\"5px\"}},{\"selector\":\"edge.highlighted\",\"style\":{\"line-color\":\"cyan\"}},{\"selector\":\"node.highlighted\",\"style\":{\"border-color\":\"cyan\",\"border-width\":\"5px\"}},{\"selector\":\"edge.highlighted\",\"style\":{\"line-color\":\"cyan\"}},{\"selector\":\"node.highlighted\",\"style\":{\"border-color\":\"cyan\",\"border-width\":\"5px\"}},{\"selector\":\"edge.highlighted\",\"style\":{\"line-color\":\"cyan\"}},{\"selector\":\"node.highlighted\",\"style\":{\"border-color\":\"cyan\",\"border-width\":\"5px\"}},{\"selector\":\"edge.highlighted\",\"style\":{\"line-color\":\"cyan\"}},{\"selector\":\"node.highlighted\",\"style\":{\"border-color\":\"cyan\",\"border-width\":\"5px\"}},{\"selector\":\"edge.highlighted\",\"style\":{\"line-color\":\"cyan\"}},{\"selector\":\"node.highlighted\",\"style\":{\"border-color\":\"cyan\",\"border-width\":\"5px\"}},{\"selector\":\"edge.highlighted\",\"style\":{\"line-color\":\"cyan\"}},{\"selector\":\"node.highlighted\",\"style\":{\"border-color\":\"cyan\",\"border-width\":\"5px\"}},{\"selector\":\"edge.highlighted\",\"style\":{\"line-color\":\"cyan\"}},{\"selector\":\"node.highlighted\",\"style\":{\"border-color\":\"cyan\",\"border-width\":\"5px\"}},{\"selector\":\"edge.highlighted\",\"style\":{\"line-color\":\"cyan\"}},{\"selector\":\"node.highlighted\",\"style\":{\"border-color\":\"cyan\",\"border-width\":\"5px\"}},{\"selector\":\"edge.highlighted\",\"style\":{\"line-color\":\"cyan\"}},{\"selector\":\"node.highlighted\",\"style\":{\"border-color\":\"cyan\",\"border-width\":\"5px\"}},{\"selector\":\"edge.highlighted\",\"style\":{\"line-color\":\"cyan\"}},{\"selector\":\"node.highlighted\",\"style\":{\"border-color\":\"cyan\",\"border-width\":\"5px\"}},{\"selector\":\"edge.highlighted\",\"style\":{\"line-color\":\"cyan\"}},{\"selector\":\"node.highlighted\",\"style\":{\"border-color\":\"cyan\",\"border-width\":\"5px\"}},{\"selector\":\"edge.highlighted\",\"style\":{\"line-color\":\"cyan\"}},{\"selector\":\"node.highlighted\",\"style\":{\"border-color\":\"cyan\",\"border-width\":\"5px\"}},{\"selector\":\"edge.highlighted\",\"style\":{\"line-color\":\"cyan\"}},{\"selector\":\"node.highlighted\",\"style\":{\"border-color\":\"cyan\",\"border-width\":\"5px\"}},{\"selector\":\"edge.highlighted\",\"style\":{\"line-color\":\"cyan\"}},{\"selector\":\"node.highlighted\",\"style\":{\"border-color\":\"cyan\",\"border-width\":\"5px\"}},{\"selector\":\"edge.highlighted\",\"style\":{\"line-color\":\"cyan\"}},{\"selector\":\"node.highlighted\",\"style\":{\"border-color\":\"cyan\",\"border-width\":\"5px\"}},{\"selector\":\"edge.highlighted\",\"style\":{\"line-color\":\"cyan\"}},{\"selector\":\"node.highlighted\",\"style\":{\"border-color\":\"cyan\",\"border-width\":\"5px\"}},{\"selector\":\"edge.highlighted\",\"style\":{\"line-color\":\"cyan\"}},{\"selector\":\"node.highlighted\",\"style\":{\"border-color\":\"cyan\",\"border-width\":\"5px\"}},{\"selector\":\"edge.highlighted\",\"style\":{\"line-color\":\"cyan\"}},{\"selector\":\"node.highlighted\",\"style\":{\"border-color\":\"cyan\",\"border-width\":\"5px\"}},{\"selector\":\"edge.highlighted\",\"style\":{\"line-color\":\"cyan\"}},{\"selector\":\"node.highlighted\",\"style\":{\"border-color\":\"cyan\",\"border-width\":\"5px\"}},{\"selector\":\"edge.highlighted\",\"style\":{\"line-color\":\"cyan\"}},{\"selector\":\"node.highlighted\",\"style\":{\"border-color\":\"cyan\",\"border-width\":\"5px\"}},{\"selector\":\"edge.highlighted\",\"style\":{\"line-color\":\"cyan\"}},{\"selector\":\"node.highlighted\",\"style\":{\"border-color\":\"cyan\",\"border-width\":\"5px\"}},{\"selector\":\"edge.highlighted\",\"style\":{\"line-color\":\"cyan\"}},{\"selector\":\"node.highlighted\",\"style\":{\"border-color\":\"cyan\",\"border-width\":\"5px\"}},{\"selector\":\"edge.highlighted\",\"style\":{\"line-color\":\"cyan\"}},{\"selector\":\"node.highlighted\",\"style\":{\"border-color\":\"cyan\",\"border-width\":\"5px\"}},{\"selector\":\"edge.highlighted\",\"style\":{\"line-color\":\"cyan\"}},{\"selector\":\"node.highlighted\",\"style\":{\"border-color\":\"cyan\",\"border-width\":\"5px\"}},{\"selector\":\"edge.highlighted\",\"style\":{\"line-color\":\"cyan\"}},{\"selector\":\"node.highlighted\",\"style\":{\"border-color\":\"cyan\",\"border-width\":\"5px\"}},{\"selector\":\"edge.highlighted\",\"style\":{\"line-color\":\"cyan\"}},{\"selector\":\"node.highlighted\",\"style\":{\"border-color\":\"cyan\",\"border-width\":\"5px\"}},{\"selector\":\"edge.highlighted\",\"style\":{\"line-color\":\"cyan\"}},{\"selector\":\"node.highlighted\",\"style\":{\"border-color\":\"cyan\",\"border-width\":\"5px\"}},{\"selector\":\"edge.highlighted\",\"style\":{\"line-color\":\"cyan\"}},{\"selector\":\"node.highlighted\",\"style\":{\"border-color\":\"cyan\",\"border-width\":\"5px\"}},{\"selector\":\"edge.highlighted\",\"style\":{\"line-color\":\"cyan\"}},{\"selector\":\"node.highlighted\",\"style\":{\"border-color\":\"cyan\",\"border-width\":\"5px\"}},{\"selector\":\"edge.highlighted\",\"style\":{\"line-color\":\"cyan\"}},{\"selector\":\"node.highlighted\",\"style\":{\"border-color\":\"cyan\",\"border-width\":\"5px\"}},{\"selector\":\"edge.highlighted\",\"style\":{\"line-color\":\"cyan\"}},{\"selector\":\"node.highlighted\",\"style\":{\"border-color\":\"cyan\",\"border-width\":\"5px\"}},{\"selector\":\"edge.highlighted\",\"style\":{\"line-color\":\"cyan\"}},{\"selector\":\"node.highlighted\",\"style\":{\"border-color\":\"cyan\",\"border-width\":\"5px\"}},{\"selector\":\"edge.highlighted\",\"style\":{\"line-color\":\"cyan\"}},{\"selector\":\"node.highlighted\",\"style\":{\"border-color\":\"cyan\",\"border-width\":\"5px\"}},{\"selector\":\"edge.highlighted\",\"style\":{\"line-color\":\"cyan\"}},{\"selector\":\"node.highlighted\",\"style\":{\"border-color\":\"cyan\",\"border-width\":\"5px\"}},{\"selector\":\"edge.highlighted\",\"style\":{\"line-color\":\"cyan\"}},{\"selector\":\"node.highlighted\",\"style\":{\"border-color\":\"cyan\",\"border-width\":\"5px\"}},{\"selector\":\"edge.highlighted\",\"style\":{\"line-color\":\"cyan\"}},{\"selector\":\"node.highlighted\",\"style\":{\"border-color\":\"cyan\",\"border-width\":\"5px\"}},{\"selector\":\"edge.highlighted\",\"style\":{\"line-color\":\"cyan\"}},{\"selector\":\"node.highlighted\",\"style\":{\"border-color\":\"cyan\",\"border-width\":\"5px\"}},{\"selector\":\"edge.highlighted\",\"style\":{\"line-color\":\"cyan\"}},{\"selector\":\"node.highlighted\",\"style\":{\"border-color\":\"cyan\",\"border-width\":\"5px\"}},{\"selector\":\"edge.highlighted\",\"style\":{\"line-color\":\"cyan\"}},{\"selector\":\"node.highlighted\",\"style\":{\"border-color\":\"cyan\",\"border-width\":\"5px\"}},{\"selector\":\"edge.highlighted\",\"style\":{\"line-color\":\"cyan\"}},{\"selector\":\"node.highlighted\",\"style\":{\"border-color\":\"cyan\",\"border-width\":\"5px\"}},{\"selector\":\"edge.highlighted\",\"style\":{\"line-color\":\"cyan\"}},{\"selector\":\"node.highlighted\",\"style\":{\"border-color\":\"cyan\",\"border-width\":\"5px\"}},{\"selector\":\"edge.highlighted\",\"style\":{\"line-color\":\"cyan\"}},{\"selector\":\"node.highlighted\",\"style\":{\"border-color\":\"cyan\",\"border-width\":\"5px\"}},{\"selector\":\"edge.highlighted\",\"style\":{\"line-color\":\"cyan\"}},{\"selector\":\"node.highlighted\",\"style\":{\"border-color\":\"cyan\",\"border-width\":\"5px\"}},{\"selector\":\"edge.highlighted\",\"style\":{\"line-color\":\"cyan\"}},{\"selector\":\"node.highlighted\",\"style\":{\"border-color\":\"cyan\",\"border-width\":\"5px\"}},{\"selector\":\"edge.highlighted\",\"style\":{\"line-color\":\"cyan\"}},{\"selector\":\"node.highlighted\",\"style\":{\"border-color\":\"cyan\",\"border-width\":\"5px\"}},{\"selector\":\"edge.highlighted\",\"style\":{\"line-color\":\"cyan\"}},{\"selector\":\"node.highlighted\",\"style\":{\"border-color\":\"cyan\",\"border-width\":\"5px\"}},{\"selector\":\"edge.highlighted\",\"style\":{\"line-color\":\"cyan\"}},{\"selector\":\"node.highlighted\",\"style\":{\"border-color\":\"cyan\",\"border-width\":\"5px\"}},{\"selector\":\"edge.highlighted\",\"style\":{\"line-color\":\"cyan\"}},{\"selector\":\"node.highlighted\",\"style\":{\"border-color\":\"cyan\",\"border-width\":\"5px\"}},{\"selector\":\"edge.highlighted\",\"style\":{\"line-color\":\"cyan\"}},{\"selector\":\"node.highlighted\",\"style\":{\"border-color\":\"cyan\",\"border-width\":\"5px\"}},{\"selector\":\"edge.highlighted\",\"style\":{\"line-color\":\"cyan\"}},{\"selector\":\"node.highlighted\",\"style\":{\"border-color\":\"cyan\",\"border-width\":\"5px\"}},{\"selector\":\"edge.highlighted\",\"style\":{\"line-color\":\"cyan\"}},{\"selector\":\"node.highlighted\",\"style\":{\"border-color\":\"cyan\",\"border-width\":\"5px\"}},{\"selector\":\"edge.highlighted\",\"style\":{\"line-color\":\"cyan\"}},{\"selector\":\"node.highlighted\",\"style\":{\"border-color\":\"cyan\",\"border-width\":\"5px\"}},{\"selector\":\"edge.highlighted\",\"style\":{\"line-color\":\"cyan\"}},{\"selector\":\"node.highlighted\",\"style\":{\"border-color\":\"cyan\",\"border-width\":\"5px\"}},{\"selector\":\"edge.highlighted\",\"style\":{\"line-color\":\"cyan\"}},{\"selector\":\"node.highlighted\",\"style\":{\"border-color\":\"cyan\",\"border-width\":\"5px\"}},{\"selector\":\"edge.highlighted\",\"style\":{\"line-color\":\"cyan\"}},{\"selector\":\"node.highlighted\",\"style\":{\"border-color\":\"cyan\",\"border-width\":\"5px\"}},{\"selector\":\"edge.highlighted\",\"style\":{\"line-color\":\"cyan\"}},{\"selector\":\"node.highlighted\",\"style\":{\"border-color\":\"cyan\",\"border-width\":\"5px\"}},{\"selector\":\"edge.highlighted\",\"style\":{\"line-color\":\"cyan\"}},{\"selector\":\"node.highlighted\",\"style\":{\"border-color\":\"cyan\",\"border-width\":\"5px\"}},{\"selector\":\"edge.highlighted\",\"style\":{\"line-color\":\"cyan\"}},{\"selector\":\"node.highlighted\",\"style\":{\"border-color\":\"cyan\",\"border-width\":\"5px\"}},{\"selector\":\"edge.highlighted\",\"style\":{\"line-color\":\"cyan\"}},{\"selector\":\"node.highlighted\",\"style\":{\"border-color\":\"cyan\",\"border-width\":\"5px\"}},{\"selector\":\"edge.highlighted\",\"style\":{\"line-color\":\"cyan\"}},{\"selector\":\"node.highlighted\",\"style\":{\"border-color\":\"cyan\",\"border-width\":\"5px\"}},{\"selector\":\"edge.highlighted\",\"style\":{\"line-color\":\"cyan\"}},{\"selector\":\"node.highlighted\",\"style\":{\"border-color\":\"cyan\",\"border-width\":\"5px\"}}],\"zoomingEnabled\":true,\"userZoomingEnabled\":true,\"zoom\":1,\"minZoom\":0.5,\"maxZoom\":3,\"panningEnabled\":true,\"userPanningEnabled\":true,\"pan\":{\"x\":1092.0302391201872,\"y\":298.0195039980433},\"boxSelectionEnabled\":true,\"renderer\":{\"name\":\"canvas\"}}",
    "nodes": "[\n    {\n        \"variables\": {},\n        \"rules\": [\n            {\n                \"rule_text\": \"SOURCE 0 thorns : 2600;\",\n                \"code\": \"Graph.create_resource('thorns', Graph.get_nodes()['Node2']).increment(2600);\",\n                \"rule_type\": \"SOURCE\",\n                \"layer\": 0\n            },\n            {\n                \"rule_text\": \"SOURCE 0 strength : 450;\",\n                \"code\": \"Graph.create_resource('strength', Graph.get_nodes()['Node2']).increment(450);\",\n                \"rule_type\": \"SOURCE\",\n                \"layer\": 0\n            },\n            {\n                \"rule_text\": \"SOURCE 0 invoker_pieces : 1;\",\n                \"code\": \"Graph.create_resource('invoker_pieces', Graph.get_nodes()['Node2']).increment(1);\",\n                \"rule_type\": \"SOURCE\",\n                \"layer\": 0\n            }\n        ],\n        \"id\": \"Node2\"\n    },\n    {\n        \"variables\": {},\n        \"rules\": [\n            {\n                \"rule_text\": \"SOURCE 0 thorns : 2600;\",\n                \"code\": \"Graph.create_resource('thorns', Graph.get_nodes()['Node3']).increment(2600);\",\n                \"rule_type\": \"SOURCE\",\n                \"layer\": 0\n            },\n            {\n                \"rule_text\": \"SOURCE 0 strength : 650;\",\n                \"code\": \"Graph.create_resource('strength', Graph.get_nodes()['Node3']).increment(650);\",\n                \"rule_type\": \"SOURCE\",\n                \"layer\": 0\n            },\n            {\n                \"rule_text\": \"SOURCE 0 invoker_pieces : 1;\",\n                \"code\": \"Graph.create_resource('invoker_pieces', Graph.get_nodes()['Node3']).increment(1);\",\n                \"rule_type\": \"SOURCE\",\n                \"layer\": 0\n            }\n        ],\n        \"id\": \"Node3\"\n    },\n    {\n        \"variables\": {},\n        \"rules\": [\n            {\n                \"rule_text\": \"SOURCE 0 thorns : 2600;\",\n                \"code\": \"Graph.create_resource('thorns', Graph.get_nodes()['Node4']).increment(2600);\",\n                \"rule_type\": \"SOURCE\",\n                \"layer\": 0\n            },\n            {\n                \"rule_text\": \"SOURCE 0 strength : 450;\",\n                \"code\": \"Graph.create_resource('strength', Graph.get_nodes()['Node4']).increment(450);\",\n                \"rule_type\": \"SOURCE\",\n                \"layer\": 0\n            },\n            {\n                \"rule_text\": \"SOURCE 0 invoker_pieces : 1;\",\n                \"code\": \"Graph.create_resource('invoker_pieces', Graph.get_nodes()['Node4']).increment(1);\",\n                \"rule_type\": \"SOURCE\",\n                \"layer\": 0\n            }\n        ],\n        \"id\": \"Node4\"\n    },\n    {\n        \"variables\": {},\n        \"rules\": [\n            {\n                \"rule_text\": \"SOURCE 0 thorns : 2000;\",\n                \"code\": \"Graph.create_resource('thorns', Graph.get_nodes()['Node5']).increment(2000);\",\n                \"rule_type\": \"SOURCE\",\n                \"layer\": 0\n            },\n            {\n                \"rule_text\": \"SOURCE 0 strength : 600;\",\n                \"code\": \"Graph.create_resource('strength', Graph.get_nodes()['Node5']).increment(600);\",\n                \"rule_type\": \"SOURCE\",\n                \"layer\": 0\n            },\n            {\n                \"rule_text\": \"SOURCE 0 invoker_pieces : 1;\",\n                \"code\": \"Graph.create_resource('invoker_pieces', Graph.get_nodes()['Node5']).increment(1);\",\n                \"rule_type\": \"SOURCE\",\n                \"layer\": 0\n            }\n        ],\n        \"id\": \"Node5\"\n    },\n    {\n        \"variables\": {},\n        \"rules\": [\n            {\n                \"rule_text\": \"SOURCE 0 thorns : 6000;\",\n                \"code\": \"Graph.create_resource('thorns', Graph.get_nodes()['Node6']).increment(6000);\",\n                \"rule_type\": \"SOURCE\",\n                \"layer\": 0\n            },\n            {\n                \"rule_text\": \"SOURCE 0 strength : 450;\",\n                \"code\": \"Graph.create_resource('strength', Graph.get_nodes()['Node6']).increment(450);\",\n                \"rule_type\": \"SOURCE\",\n                \"layer\": 0\n            },\n            {\n                \"rule_text\": \"SOURCE 0 invoker_pieces : 1;\",\n                \"code\": \"Graph.create_resource('invoker_pieces', Graph.get_nodes()['Node6']).increment(1);\",\n                \"rule_type\": \"SOURCE\",\n                \"layer\": 0\n            }\n        ],\n        \"id\": \"Node6\"\n    },\n    {\n        \"variables\": {},\n        \"rules\": [\n            {\n                \"rule_text\": \"SOURCE 0 thorns : 2400;\",\n                \"code\": \"Graph.create_resource('thorns', Graph.get_nodes()['Node7']).increment(2400);\",\n                \"rule_type\": \"SOURCE\",\n                \"layer\": 0\n            },\n            {\n                \"rule_text\": \"SOURCE 0 strength : 450;\",\n                \"code\": \"Graph.create_resource('strength', Graph.get_nodes()['Node7']).increment(450);\",\n                \"rule_type\": \"SOURCE\",\n                \"layer\": 0\n            },\n            {\n                \"rule_text\": \"SOURCE 0 invoker_pieces : 1;\",\n                \"code\": \"Graph.create_resource('invoker_pieces', Graph.get_nodes()['Node7']).increment(1);\",\n                \"rule_type\": \"SOURCE\",\n                \"layer\": 0\n            }\n        ],\n        \"id\": \"Node7\"\n    },\n    {\n        \"variables\": {},\n        \"rules\": [\n            {\n                \"rule_text\": \"SOURCE 0 thorns_multiplier : if ( invoker_pieces == 2 ) then 35 else if ( invoker_pieces == 6 ) then 50 else 0 endif endif;\",\n                \"code\": \"Graph.create_resource('thorns_multiplier', Graph.get_nodes()['Node8']).increment(((Graph.create_resource('invoker_pieces', Graph.get_nodes()['Node8']).value===2) ? 35 : ((Graph.create_resource('invoker_pieces', Graph.get_nodes()['Node8']).value===6) ? 50 : 0)));\",\n                \"rule_type\": \"SOURCE\",\n                \"layer\": 0\n            },\n            {\n                \"rule_text\": \"SINK 0 invoker_pieces : invoker_pieces;\",\n                \"code\": \"Graph.create_resource('invoker_pieces', Graph.get_nodes()['Node8']).decrement(Graph.create_resource('invoker_pieces', Graph.get_nodes()['Node8']).value);\",\n                \"rule_type\": \"SINK\",\n                \"layer\": 0\n            }\n        ],\n        \"id\": \"Node8\"\n    },\n    {\n        \"variables\": {},\n        \"rules\": [],\n        \"id\": \"Node9\"\n    },\n    {\n        \"variables\": {\n            \"damage\": {\n                \"name\": \"damage\",\n                \"current_value\": 30,\n                \"initial_value\": 30\n            }\n        },\n        \"rules\": [\n            {\n                \"rule_text\": \"INTERNAL VAR damage = 30;\",\n                \"code\": \"Graph.get_nodes()['Node10'].variables['damage'] = {name:'damage',current_value:30,initial_value:30,max_value:undefined,min_value:undefined,reset_value:undefined}\",\n                \"rule_type\": \"INTERNAL VAR\"\n            },\n            {\n                \"rule_text\": \"SOURCE 0 thorns_multiplier : random ( 75 : 100 );\",\n                \"code\": \"Graph.create_resource('thorns_multiplier', Graph.get_nodes()['Node10']).increment(Math.floor(Math.random() * 25 + 75));\",\n                \"rule_type\": \"SOURCE\",\n                \"layer\": 0\n            },\n            {\n                \"rule_text\": \"SOURCE 0 strength : 150;\",\n                \"code\": \"Graph.create_resource('strength', Graph.get_nodes()['Node10']).increment(150);\",\n                \"rule_type\": \"SOURCE\",\n                \"layer\": 0\n            },\n            {\n                \"rule_text\": \"SOURCE 1 weapon_damage : attack_speed * damage;\",\n                \"code\": \"Graph.create_resource('weapon_damage', Graph.get_nodes()['Node10']).increment(Graph.create_resource('attack_speed', Graph.get_nodes()['Node10']).value*Graph.get_nodes()['Node10'].variables['damage'].current_value);\",\n                \"rule_type\": \"SOURCE\",\n                \"layer\": 1\n            },\n            {\n                \"rule_text\": \"SOURCE 0 attack_speed : 1;\",\n                \"code\": \"Graph.create_resource('attack_speed', Graph.get_nodes()['Node10']).increment(1);\",\n                \"rule_type\": \"SOURCE\",\n                \"layer\": 0\n            }\n        ],\n        \"id\": \"Node10\"\n    },\n    {\n        \"variables\": {},\n        \"rules\": [\n            {\n                \"rule_text\": \"SOURCE 0 strength : 150;\",\n                \"code\": \"Graph.create_resource('strength', Graph.get_nodes()['Node11']).increment(150);\",\n                \"rule_type\": \"SOURCE\",\n                \"layer\": 0\n            },\n            {\n                \"rule_text\": \"SOURCE 3 block_successful : if ( random ( 0 : 100 ) < block_chance ) then 1 else 0 endif;\",\n                \"code\": \"Graph.create_resource('block_successful', Graph.get_nodes()['Node11']).increment(((Math.floor(Math.random() * 100 + 0)<Graph.create_resource('block_chance', Graph.get_nodes()['Node11']).value) ? 1 : 0));\",\n                \"rule_type\": \"SOURCE\",\n                \"layer\": 3\n            },\n            {\n                \"rule_text\": \"SOURCE 2 block_chance : if ( ( block_chance + 6 ) > 100 ) then 100 else block_chance + 6 endif;\",\n                \"code\": \"Graph.create_resource('block_chance', Graph.get_nodes()['Node11']).increment((((Graph.create_resource('block_chance', Graph.get_nodes()['Node11']).value+6)>100) ? 100 : Graph.create_resource('block_chance', Graph.get_nodes()['Node11']).value+6));\",\n                \"rule_type\": \"SOURCE\",\n                \"layer\": 2\n            },\n            {\n                \"rule_text\": \"SINK 0 block_chance : block_chance;\",\n                \"code\": \"Graph.create_resource('block_chance', Graph.get_nodes()['Node11']).decrement(Graph.create_resource('block_chance', Graph.get_nodes()['Node11']).value);\",\n                \"rule_type\": \"SINK\",\n                \"layer\": 0\n            },\n            {\n                \"rule_text\": \"SINK 0 block_successful : if ( block_successful > 0 ) then block_successful else 0 endif;\",\n                \"code\": \"Graph.create_resource('block_successful', Graph.get_nodes()['Node11']).decrement(((Graph.create_resource('block_successful', Graph.get_nodes()['Node11']).value>0) ? Graph.create_resource('block_successful', Graph.get_nodes()['Node11']).value : 0));\",\n                \"rule_type\": \"SINK\",\n                \"layer\": 0\n            }\n        ],\n        \"id\": \"Node11\"\n    },\n    {\n        \"variables\": {},\n        \"rules\": [\n            {\n                \"rule_text\": \"SOURCE 0 strength : 300;\",\n                \"code\": \"Graph.create_resource('strength', Graph.get_nodes()['Node12']).increment(300);\",\n                \"rule_type\": \"SOURCE\",\n                \"layer\": 0\n            }\n        ],\n        \"id\": \"Node12\"\n    },\n    {\n        \"variables\": {},\n        \"rules\": [\n            {\n                \"rule_text\": \"SOURCE 0 damage_multiplier : 100;\",\n                \"code\": \"Graph.create_resource('damage_multiplier', Graph.get_nodes()['Node13']).increment(100);\",\n                \"rule_type\": \"SOURCE\",\n                \"layer\": 0\n            }\n        ],\n        \"id\": \"Node13\"\n    },\n    {\n        \"variables\": {},\n        \"rules\": [\n            {\n                \"rule_text\": \"SOURCE 1 thorns : 2.5* vitality;\",\n                \"code\": \"Graph.create_resource('thorns', Graph.get_nodes()['Node14']).increment(2.5Graph.create_resource('vitality', Graph.get_nodes()['Node14']).value);\",\n                \"rule_type\": \"SOURCE\",\n                \"layer\": 1\n            }\n        ],\n        \"id\": \"Node14\"\n    },\n    {\n        \"variables\": {},\n        \"rules\": [\n            {\n                \"rule_text\": \"SOURCE 0 thorns : 16000;\",\n                \"code\": \"Graph.create_resource('thorns', Graph.get_nodes()['Node15']).increment(16000);\",\n                \"rule_type\": \"SOURCE\",\n                \"layer\": 0\n            },\n            {\n                \"rule_text\": \"SOURCE 0 gems : 1;\",\n                \"code\": \"Graph.create_resource('gems', Graph.get_nodes()['Node15']).increment(1);\",\n                \"rule_type\": \"SOURCE\",\n                \"layer\": 0\n            },\n            {\n                \"rule_text\": \"SINK 0 gems : 1;\",\n                \"code\": \"Graph.create_resource('gems', Graph.get_nodes()['Node15']).decrement(1);\",\n                \"rule_type\": \"SINK\",\n                \"layer\": 0\n            }\n        ],\n        \"id\": \"Node15\"\n    },\n    {\n        \"variables\": {},\n        \"rules\": [\n            {\n                \"rule_text\": \"SOURCE 0 block_chance : 30;\",\n                \"code\": \"Graph.create_resource('block_chance', Graph.get_nodes()['Node16']).increment(30);\",\n                \"rule_type\": \"SOURCE\",\n                \"layer\": 0\n            },\n            {\n                \"rule_text\": \"SINK 0 dodge_chance : 100;\",\n                \"code\": \"Graph.create_resource('dodge_chance', Graph.get_nodes()['Node16']).decrement(100);\",\n                \"rule_type\": \"SINK\",\n                \"layer\": 0\n            }\n        ],\n        \"id\": \"Node16\"\n    },\n    {\n        \"variables\": {},\n        \"rules\": [\n            {\n                \"rule_text\": \"SOURCE 1 strength_multiplier : 1.5 * gems;\",\n                \"code\": \"Graph.create_resource('strength_multiplier', Graph.get_nodes()['Node17']).increment(1.5*Graph.create_resource('gems', Graph.get_nodes()['Node17']).value);\",\n                \"rule_type\": \"SOURCE\",\n                \"layer\": 1\n            }\n        ],\n        \"id\": \"Node17\"\n    },\n    {\n        \"variables\": {},\n        \"rules\": [\n            {\n                \"rule_text\": \"SOURCE 0 attack_speed : 15;\",\n                \"code\": \"Graph.create_resource('attack_speed', Graph.get_nodes()['Node18']).increment(15);\",\n                \"rule_type\": \"SOURCE\",\n                \"layer\": 0\n            }\n        ],\n        \"id\": \"Node18\"\n    },\n    {\n        \"variables\": {},\n        \"rules\": [\n            {\n                \"rule_text\": \"SOURCE 0 thorns_multiplier : 50;\",\n                \"code\": \"Graph.create_resource('thorns_multiplier', Graph.get_nodes()['Node19']).increment(50);\",\n                \"rule_type\": \"SOURCE\",\n                \"layer\": 0\n            }\n        ],\n        \"id\": \"Node19\"\n    },\n    {\n        \"variables\": {},\n        \"rules\": [],\n        \"id\": \"Node20\"\n    },\n    {\n        \"variables\": {\n            \"wrath_supply\": {\n                \"name\": \"wrath_supply\",\n                \"current_value\": 0,\n                \"initial_value\": 0,\n                \"max_value\": 100,\n                \"min_value\": 0\n            }\n        },\n        \"rules\": [\n            {\n                \"rule_text\": \"INTERNAL VAR wrath_supply = 0 min = 0 max = 100;\",\n                \"code\": \"Graph.get_nodes()['Node21'].variables['wrath_supply'] = {name:'wrath_supply',current_value:0,initial_value:0,max_value:100,min_value:0,reset_value:undefined}\",\n                \"rule_type\": \"INTERNAL VAR\"\n            },\n            {\n                \"rule_text\": \"SOURCE 0 strength : 210;\",\n                \"code\": \"Graph.create_resource('strength', Graph.get_nodes()['Node21']).increment(210);\",\n                \"rule_type\": \"SOURCE\",\n                \"layer\": 0\n            },\n            {\n                \"rule_text\": \"SOURCE 0 vitality : 140;\",\n                \"code\": \"Graph.create_resource('vitality', Graph.get_nodes()['Node21']).increment(140);\",\n                \"rule_type\": \"SOURCE\",\n                \"layer\": 0\n            },\n            {\n                \"rule_text\": \"SINK 4 thorns : thorns;\",\n                \"code\": \"Graph.create_resource('thorns', Graph.get_nodes()['Node21']).decrement(Graph.create_resource('thorns', Graph.get_nodes()['Node21']).value);\",\n                \"rule_type\": \"SINK\",\n                \"layer\": 4\n            },\n            {\n                \"rule_text\": \"SOURCE 5 thorns_damage : weapon_damage + strength + thorns * thorns_multiplier;\",\n                \"code\": \"Graph.create_resource('thorns_damage', Graph.get_nodes()['Node21']).increment(Graph.create_resource('weapon_damage', Graph.get_nodes()['Node21']).value+Graph.create_resource('strength', Graph.get_nodes()['Node21']).value+Graph.create_resource('thorns', Graph.get_nodes()['Node21']).value*Graph.create_resource('thorns_multiplier', Graph.get_nodes()['Node21']).value);\",\n                \"rule_type\": \"SOURCE\",\n                \"layer\": 5\n            }\n        ],\n        \"id\": \"Node21\"\n    },\n    {\n        \"variables\": {},\n        \"rules\": [\n            {\n                \"rule_text\": \"SOURCE 1 block_chance : if ( hardened_senses > 0 ) then 15 else 0 endif;\",\n                \"code\": \"Graph.create_resource('block_chance', Graph.get_nodes()['Node22']).increment(((Graph.create_resource('hardened_senses', Graph.get_nodes()['Node22']).value>0) ? 15 : 0));\",\n                \"rule_type\": \"SOURCE\",\n                \"layer\": 1\n            },\n            {\n                \"rule_text\": \"SINK 0 hardened_senses : if ( hardened_senses > 0 ) then 1 else 0 endif;\",\n                \"code\": \"Graph.create_resource('hardened_senses', Graph.get_nodes()['Node22']).decrement(((Graph.create_resource('hardened_senses', Graph.get_nodes()['Node22']).value>0) ? 1 : 0));\",\n                \"rule_type\": \"SINK\",\n                \"layer\": 0\n            }\n        ],\n        \"id\": \"Node22\"\n    },\n    {\n        \"variables\": {},\n        \"rules\": [\n            {\n                \"rule_text\": \"SOURCE 4 attack_speed_multiplier : if ( block_successful == 1 ) then 15 else 0 endif;\",\n                \"code\": \"Graph.create_resource('attack_speed_multiplier', Graph.get_nodes()['Node23']).increment(((Graph.create_resource('block_successful', Graph.get_nodes()['Node23']).value===1) ? 15 : 0));\",\n                \"rule_type\": \"SOURCE\",\n                \"layer\": 4\n            }\n        ],\n        \"id\": \"Node23\"\n    },\n    {\n        \"variables\": {},\n        \"rules\": [],\n        \"id\": \"Node24\"\n    },\n    {\n        \"variables\": {},\n        \"rules\": [\n            {\n                \"rule_text\": \"SOURCE 0 wrath : 5;\",\n                \"code\": \"Graph.create_resource('wrath', Graph.get_nodes()['Node25']).increment(5);\",\n                \"rule_type\": \"SOURCE\",\n                \"layer\": 0\n            },\n            {\n                \"rule_text\": \"SOURCE 0 weapon_damage_multiplier : 335;\",\n                \"code\": \"Graph.create_resource('weapon_damage_multiplier', Graph.get_nodes()['Node25']).increment(335);\",\n                \"rule_type\": \"SOURCE\",\n                \"layer\": 0\n            },\n            {\n                \"rule_text\": \"SOURCE 0 hardened_senses : 5;\",\n                \"code\": \"Graph.create_resource('hardened_senses', Graph.get_nodes()['Node25']).increment(5);\",\n                \"rule_type\": \"SOURCE\",\n                \"layer\": 0\n            },\n            {\n                \"rule_text\": \"SOURCE 0 punish : 1;\",\n                \"code\": \"Graph.create_resource('punish', Graph.get_nodes()['Node25']).increment(1);\",\n                \"rule_type\": \"SOURCE\",\n                \"layer\": 0\n            }\n        ],\n        \"id\": \"Node25\"\n    }\n]"
}